ColorInfo_liumou_Stable/__init__.py
ColorInfo_liumou_Stable/colors.py
ColorInfo_liumou_Stable/file_manager.py
ColorInfo_liumou_Stable/formatter.py
ColorInfo_liumou_Stable/inspector.py
ColorInfo_liumou_Stable/levels.py
ColorInfo_liumou_Stable/logger.py
ColorInfo_liumou_Stable/structured.py
colorinfo_liumou_stable-2.0.1.dist-info/METADATA
colorinfo_liumou_stable-2.0.1.dist-info/WHEEL
colorinfo_liumou_stable-2.0.1.dist-info/licenses/LICENSE
colorinfo_liumou_stable-2.0.1.dist-info/RECORD
