Metadata-Version: 2.4
Name: ColorInfo_liumou_Stable
Version: 2.0.1
Summary: 功能强大的 Python 彩色日志工具，支持结构化日志记录，类似 Go Zap 的字段式日志，支持纯文本和 JSON 格式输出
Project-URL: Homepage, https://gitee.com/liumou_site/ColorInfo
Project-URL: Bug Tracker, https://gitee.com/liumou_site/ColorInfo/issues
Project-URL: Documentation, https://gitee.com/liumou_site/ColorInfo/blob/master/README.md
Project-URL: Repository, https://gitee.com/liumou_site/ColorInfo.git
Project-URL: PyPI, https://pypi.org/project/ColorInfo_liumou_Stable/
Author-email: 坐公交也用券 <liumou.site@qq.com>
License: MIT
License-File: LICENSE
Keywords: color,debug,json,logger,logging,structured-logging,terminal,zap,彩色日志,结构化日志
Classifier: Development Status :: 5 - Production/Stable
Classifier: Intended Audience :: Developers
Classifier: License :: OSI Approved :: MIT License
Classifier: Operating System :: OS Independent
Classifier: Programming Language :: Python :: 3
Classifier: Programming Language :: Python :: 3.0
Classifier: Programming Language :: Python :: 3.5
Classifier: Programming Language :: Python :: 3.6
Classifier: Programming Language :: Python :: 3.7
Classifier: Programming Language :: Python :: 3.8
Classifier: Programming Language :: Python :: 3.9
Classifier: Programming Language :: Python :: 3.10
Classifier: Programming Language :: Python :: 3.11
Classifier: Programming Language :: Python :: 3.12
Classifier: Topic :: Software Development :: Libraries :: Python Modules
Classifier: Topic :: System :: Logging
Classifier: Topic :: Utilities
Requires-Python: >=3.0
Provides-Extra: dev
Requires-Dist: black>=21.0.0; extra == 'dev'
Requires-Dist: flake8>=3.8.0; extra == 'dev'
Requires-Dist: mypy>=0.800; extra == 'dev'
Requires-Dist: pytest-cov>=2.0.0; extra == 'dev'
Requires-Dist: pytest>=3.0.0; extra == 'dev'
Provides-Extra: test
Requires-Dist: pytest-cov>=2.0.0; extra == 'test'
Requires-Dist: pytest>=3.0.0; extra == 'test'
